{"type":"FeatureCollection","version":7,"region":"macau","macro_region":"macau","updated":"2026-07-12T03:01:13.961Z","source":"overpass","features":[{"type":"Feature","geometry":{"type":"LineString","coordinates":[[113.54617,22.21797],[113.54153,22.21803]]},"properties":{"osm_id":165636516,"osm_type":"way","macro_region":"macau","railway_type":"highspeed","color":"#E60012","line_name":"广珠城际线","name":"广珠城际线","name:en":"Guangzhou–Zhuhai Intercity Railway","name_en":"Guangzhou–Zhuhai Intercity Railway","name:zh":"广珠城际线"}},{"type":"Feature","geometry":{"type":"LineString","coordinates":[[113.54156,22.15694],[113.54097,22.1587],[113.54075,22.15965],[113.54061,22.16074]]},"properties":{"osm_id":277071239,"osm_type":"way","macro_region":"macau","railway_type":"tram","color":"#9B1096","line_name":"澳門輕軌氹仔線 Linha de Taipa do ML M","name":"澳門輕軌氹仔線 Linha de Taipa do ML M","name:en":"Taipa Line of Macao LRT","name_en":"Taipa Line of Macao LRT","name:zh-Hant":"澳門輕軌氹仔線"}},{"type":"Feature","geometry":{"type":"LineString","coordinates":[[113.54616,22.21782],[113.5415,22.21791]]},"properties":{"osm_id":282682469,"osm_type":"way","macro_region":"macau","railway_type":"rail","color":"#003DA5","line_name":null}},{"type":"Feature","geometry":{"type":"LineString","coordinates":[[113.5415,22.21791],[113.54063,22.21798],[113.54005,22.21793]]},"properties":{"osm_id":282682470,"osm_type":"way","macro_region":"macau","railway_type":"rail","color":"#003DA5","line_name":"珠海联络线","name":"珠海联络线"}},{"type":"Feature","geometry":{"type":"LineString","coordinates":[[113.53604,22.10719],[113.53236,22.1055],[113.53138,22.10512],[113.53055,22.10482],[113.52891,22.10445],[113.52608,22.10423],[113.52396,22.10421],[113.52186,22.10439],[113.52066,22.10459],[113.51871,22.10506],[113.51677,22.10587],[113.50257,22.11388],[113.50099,22.11459],[113.49891,22.11518],[113.49617,22.1156],[113.49418,22.11579],[113.49246,22.11586],[113.49049,22.11581]]},"properties":{"osm_id":290155015,"osm_type":"way","macro_region":"macau","railway_type":"rail","color":"#003DA5","line_name":"珠机城际线","name":"珠机城际线","name:en":"Zhuhai-Zhuhai Airport Intercity Railway","name_en":"Zhuhai-Zhuhai Airport Intercity Railway","name:zh-Hant":"珠機城際線"}},{"type":"Feature","geometry":{"type":"LineString","coordinates":[[113.5693,22.15007],[113.56901,22.14989],[113.56887,22.1496],[113.56918,22.14806],[113.56923,22.14668],[113.56856,22.14171],[113.56843,22.13992],[113.56828,22.13958],[113.56742,22.13886],[113.56707,22.1387],[113.56651,22.13859],[113.56407,22.13877],[113.56259,22.13873],[113.56059,22.13889],[113.5603,22.13901],[113.5593,22.14001],[113.55801,22.1402],[113.5578,22.14033],[113.55767,22.14057],[113.55772,22.1432],[113.558,22.14896],[113.55795,22.14933],[113.55777,22.14965],[113.55731,22.15],[113.55558,22.15043],[113.55171,22.15201],[113.55146,22.15217],[113.55121,22.15253],[113.55119,22.1531]]},"properties":{"osm_id":388893284,"osm_type":"way","macro_region":"macau","railway_type":"tram","color":"#9B1096","line_name":"澳門輕軌氹仔線 Linha de Taipa do ML M","name":"澳門輕軌氹仔線 Linha de Taipa do ML M","name:en":"Taipa Line of Macao LRT","name_en":"Taipa Line of Macao LRT","name:zh-Hant":"澳門輕軌氹仔線"}},{"type":"Feature","geometry":{"type":"LineString","coordinates":[[113.54153,22.21803],[113.53836,22.21808],[113.53742,22.21824],[113.53649,22.21866],[113.53555,22.21956]]},"properties":{"osm_id":402864176,"osm_type":"way","macro_region":"macau","railway_type":"highspeed","color":"#E60012","line_name":"广珠城际线","name":"广珠城际线","name:en":"Guangzhou–Zhuhai Intercity Railway","name_en":"Guangzhou–Zhuhai Intercity Railway","name:zh":"广珠城际线"}},{"type":"Feature","geometry":{"type":"LineString","coordinates":[[113.53558,22.21958],[113.53651,22.21869],[113.53717,22.21836],[113.53788,22.21817],[113.54617,22.21802]]},"properties":{"osm_id":402864182,"osm_type":"way","macro_region":"macau","railway_type":"highspeed","color":"#E60012","line_name":"广珠城际线","name":"广珠城际线","name:en":"Guangzhou–Zhuhai Intercity Railway","name_en":"Guangzhou–Zhuhai Intercity Railway","name:zh":"广珠城际线"}},{"type":"Feature","geometry":{"type":"LineString","coordinates":[[113.54061,22.16074],[113.54037,22.16262],[113.53977,22.16488]]},"properties":{"osm_id":445281246,"osm_type":"way","macro_region":"macau","railway_type":"tram","color":"#9B1096","line_name":"澳門輕軌氹仔線 Linha de Taipa do ML M","name":"澳門輕軌氹仔線 Linha de Taipa do ML M","name:en":"Taipa Line of Macao LRT","name_en":"Taipa Line of Macao LRT","name:zh-Hant":"澳門輕軌氹仔線"}},{"type":"Feature","geometry":{"type":"LineString","coordinates":[[113.52935,22.18389],[113.52955,22.18233],[113.52979,22.18188],[113.53033,22.18124],[113.53075,22.18088],[113.53208,22.18022]]},"properties":{"osm_id":446757088,"osm_type":"way","macro_region":"macau","railway_type":"tram","color":"#9B1096","line_name":"澳門輕軌氹仔線 Linha de Taipa do ML M","name":"澳門輕軌氹仔線 Linha de Taipa do ML M","name:en":"Taipa Line of Macao LRT","name_en":"Taipa Line of Macao LRT","name:zh-Hant":"澳門輕軌氹仔線"}},{"type":"Feature","geometry":{"type":"LineString","coordinates":[[113.53977,22.16488],[113.53941,22.16583]]},"properties":{"osm_id":446757089,"osm_type":"way","macro_region":"macau","railway_type":"tram","color":"#9B1096","line_name":"澳門輕軌氹仔線 Linha de Taipa do ML M","name":"澳門輕軌氹仔線 Linha de Taipa do ML M","name:en":"Taipa Line of Macao LRT","name_en":"Taipa Line of Macao LRT","name:zh":"澳門輕軌氹仔線"}},{"type":"Feature","geometry":{"type":"LineString","coordinates":[[113.54165,22.15696],[113.54196,22.15633],[113.54212,22.1562],[113.54242,22.15612],[113.54277,22.15624],[113.5431,22.15656],[113.54341,22.15673],[113.54426,22.15703],[113.54476,22.15711],[113.54905,22.15713],[113.55129,22.157],[113.55211,22.15678],[113.55277,22.15649],[113.553,22.15628],[113.55305,22.15606],[113.55293,22.15578],[113.55226,22.15508]]},"properties":{"osm_id":520187034,"osm_type":"way","macro_region":"macau","railway_type":"tram","color":"#9B1096","line_name":"澳門輕軌氹仔線 Linha de Taipa do ML M","name":"澳門輕軌氹仔線 Linha de Taipa do ML M","name:en":"Taipa Line of Macao LRT","name_en":"Taipa Line of Macao LRT","name:zh-Hant":"澳門輕軌氹仔線"}},{"type":"Feature","geometry":{"type":"LineString","coordinates":[[113.54165,22.15696],[113.54095,22.15904],[113.54072,22.16074]]},"properties":{"osm_id":520187042,"osm_type":"way","macro_region":"macau","railway_type":"tram","color":"#9B1096","line_name":"澳門輕軌氹仔線 Linha de Taipa do ML M","name":"澳門輕軌氹仔線 Linha de Taipa do ML M","name:en":"Taipa Line of Macao LRT","name_en":"Taipa Line of Macao LRT","name:zh-Hant":"澳門輕軌氹仔線"}},{"type":"Feature","geometry":{"type":"LineString","coordinates":[[113.52416,22.21262],[113.5249,22.21325]]},"properties":{"osm_id":554325762,"osm_type":"way","macro_region":"macau","railway_type":"rail","color":"#003DA5","line_name":"珠机城际线","name":"珠机城际线","name:en":"Zhuhai-Zhuhai Airport Intercity Railway","name_en":"Zhuhai-Zhuhai Airport Intercity Railway","name:zh":"珠机城际线"}},{"type":"Feature","geometry":{"type":"LineString","coordinates":[[113.54072,22.16074],[113.54058,22.16216],[113.5402,22.16385],[113.53987,22.16491]]},"properties":{"osm_id":579113746,"osm_type":"way","macro_region":"macau","railway_type":"tram","color":"#9B1096","line_name":"澳門輕軌氹仔線 Linha de Taipa do ML M","name":"澳門輕軌氹仔線 Linha de Taipa do ML M","name:en":"Taipa Line of Macao LRT","name_en":"Taipa Line of Macao LRT","name:zh-Hant":"澳門輕軌氹仔線"}},{"type":"Feature","geometry":{"type":"LineString","coordinates":[[113.5249,22.21325],[113.52545,22.21358],[113.5267,22.21396],[113.53236,22.21503],[113.53353,22.21532],[113.5351,22.21585],[113.53899,22.21738],[113.54156,22.21765],[113.54386,22.21764]]},"properties":{"osm_id":579283414,"osm_type":"way","macro_region":"macau","railway_type":"rail","color":"#003DA5","line_name":"珠机城际线","name":"珠机城际线","name:en":"Zhuhai-Zhuhai Airport Intercity Railway","name_en":"Zhuhai-Zhuhai Airport Intercity Railway","name:zh":"珠机城际线"}},{"type":"Feature","geometry":{"type":"LineString","coordinates":[[113.56185,22.13146],[113.56226,22.13145],[113.56263,22.13158],[113.56286,22.13185],[113.56295,22.1321],[113.56322,22.13793]]},"properties":{"osm_id":620888026,"osm_type":"way","macro_region":"macau","railway_type":"tram","color":"#9B1096","line_name":"澳門輕軌石排灣線 Linha de Seac Pai Van do ML M","name":"澳門輕軌石排灣線 Linha de Seac Pai Van do ML M","name:en":"Seac Pai Van Line of Macao LRT","name_en":"Seac Pai Van Line of Macao LRT","name:zh-Hant":"澳門輕軌石排灣線"}},{"type":"Feature","geometry":{"type":"LineString","coordinates":[[113.53947,22.16586],[113.53987,22.16491]]},"properties":{"osm_id":624638694,"osm_type":"way","macro_region":"macau","railway_type":"tram","color":"#9B1096","line_name":"澳門輕軌氹仔線 Linha de Taipa do ML M","name":"澳門輕軌氹仔線 Linha de Taipa do ML M","name:en":"Taipa Line of Macao LRT","name_en":"Taipa Line of Macao LRT","name:zh":"澳門輕軌氹仔線"}},{"type":"Feature","geometry":{"type":"LineString","coordinates":[[113.53208,22.18022],[113.53232,22.17993],[113.53318,22.17827],[113.53941,22.16583]]},"properties":{"osm_id":624638696,"osm_type":"way","macro_region":"macau","railway_type":"tram","color":"#9B1096","line_name":"澳門輕軌氹仔線 Linha de Taipa do ML M","name":"澳門輕軌氹仔線 Linha de Taipa do ML M","name:en":"Taipa Line of Macao LRT","name_en":"Taipa Line of Macao LRT","name:zh-Hant":"澳門輕軌氹仔線"}},{"type":"Feature","geometry":{"type":"LineString","coordinates":[[113.53214,22.18024],[113.53243,22.17986],[113.53947,22.16586]]},"properties":{"osm_id":624638697,"osm_type":"way","macro_region":"macau","railway_type":"tram","color":"#9B1096","line_name":"澳門輕軌氹仔線 Linha de Taipa do ML M","name":"澳門輕軌氹仔線 Linha de Taipa do ML M","name:en":"Taipa Line of Macao LRT","name_en":"Taipa Line of Macao LRT","name:zh-Hant":"澳門輕軌氹仔線"}},{"type":"Feature","geometry":{"type":"LineString","coordinates":[[113.53214,22.18024],[113.53192,22.18041],[113.53081,22.18091],[113.52988,22.18194],[113.52965,22.18237],[113.52947,22.18342]]},"properties":{"osm_id":624638698,"osm_type":"way","macro_region":"macau","railway_type":"subway","color":"#E3002C","line_name":"澳門輕軌氹仔線 Linha de Taipa do ML M","name":"澳門輕軌氹仔線 Linha de Taipa do ML M","name:en":"Taipa Line of Macao LRT","name_en":"Taipa Line of Macao LRT","name:zh-Hant":"澳門輕軌氹仔線"}},{"type":"Feature","geometry":{"type":"LineString","coordinates":[[113.56856,22.14211],[113.56919,22.14689],[113.56912,22.14819],[113.56883,22.14943],[113.56884,22.14967],[113.5691,22.15001],[113.57108,22.1509],[113.57129,22.15114],[113.57138,22.15144],[113.57137,22.15184],[113.57125,22.1521],[113.56958,22.15476],[113.56947,22.15507],[113.56954,22.15556],[113.56995,22.156],[113.57352,22.15761],[113.57408,22.15804],[113.57431,22.15837],[113.57451,22.15886],[113.57469,22.15985],[113.57506,22.16073],[113.57544,22.16202],[113.57537,22.16243],[113.57505,22.16271],[113.57123,22.16364]]},"properties":{"osm_id":754856890,"osm_type":"way","macro_region":"macau","railway_type":"tram","color":"#9B1096","line_name":"澳門輕軌氹仔線 Linha de Taipa do ML M","name":"澳門輕軌氹仔線 Linha de Taipa do ML M","name:en":"Taipa Line of Macao LRT","name_en":"Taipa Line of Macao LRT","name:zh-Hant":"澳門輕軌氹仔線"}},{"type":"Feature","geometry":{"type":"LineString","coordinates":[[113.56333,22.13738],[113.56314,22.13535],[113.56296,22.13194],[113.56271,22.13158],[113.56247,22.13142],[113.56123,22.1314]]},"properties":{"osm_id":774703405,"osm_type":"way","macro_region":"macau","railway_type":"tram","color":"#9B1096","line_name":"澳門輕軌石排灣線 Linha de Seac Pai Van do ML M","name":"澳門輕軌石排灣線 Linha de Seac Pai Van do ML M","name:en":"Seac Pai Van Line of Macao LRT","name_en":"Seac Pai Van Line of Macao LRT","name:zh-Hant":"澳門輕軌石排灣線"}},{"type":"Feature","geometry":{"type":"LineString","coordinates":[[113.55226,22.15508],[113.55125,22.15307]]},"properties":{"osm_id":814635017,"osm_type":"way","macro_region":"macau","railway_type":"tram","color":"#9B1096","line_name":"澳門輕軌氹仔線 Linha de Taipa do ML M","name":"澳門輕軌氹仔線 Linha de Taipa do ML M","name:en":"Taipa Line of Macao LRT","name_en":"Taipa Line of Macao LRT","name:zh":"澳門輕軌氹仔線"}},{"type":"Feature","geometry":{"type":"LineString","coordinates":[[113.5522,22.1551],[113.55289,22.15582],[113.55298,22.156],[113.55297,22.1562],[113.55274,22.15644],[113.55177,22.15684],[113.55128,22.15695],[113.54907,22.15708],[113.54483,22.15706],[113.54425,22.15697],[113.54339,22.15667],[113.5428,22.15618],[113.54238,22.15606],[113.54196,22.15621],[113.54156,22.15694]]},"properties":{"osm_id":814635018,"osm_type":"way","macro_region":"macau","railway_type":"tram","color":"#9B1096","line_name":"澳門輕軌氹仔線 Linha de Taipa do ML M","name":"澳門輕軌氹仔線 Linha de Taipa do ML M","name:en":"Taipa Line of Macao LRT","name_en":"Taipa Line of Macao LRT","name:zh-Hant":"澳門輕軌氹仔線"}},{"type":"Feature","geometry":{"type":"LineString","coordinates":[[113.55119,22.1531],[113.5522,22.1551]]},"properties":{"osm_id":814979932,"osm_type":"way","macro_region":"macau","railway_type":"tram","color":"#9B1096","line_name":"澳門輕軌氹仔線 Linha de Taipa do ML M","name":"澳門輕軌氹仔線 Linha de Taipa do ML M","name:en":"Taipa Line of Macao LRT","name_en":"Taipa Line of Macao LRT","name:zh":"澳門輕軌氹仔線"}},{"type":"Feature","geometry":{"type":"LineString","coordinates":[[113.55125,22.15307],[113.55127,22.15255],[113.5515,22.15221],[113.55174,22.15206],[113.55567,22.15045],[113.55738,22.15003],[113.55759,22.14991],[113.55794,22.14949],[113.55805,22.1489],[113.55773,22.14068],[113.55774,22.14054],[113.5579,22.14033],[113.5582,22.14021],[113.55912,22.14014],[113.55932,22.14006],[113.56025,22.13911],[113.56066,22.13893],[113.56258,22.13877],[113.56404,22.13881],[113.56669,22.13865],[113.56755,22.13899],[113.56808,22.13942],[113.56831,22.13971],[113.56839,22.13995],[113.56856,22.14211]]},"properties":{"osm_id":814979933,"osm_type":"way","macro_region":"macau","railway_type":"tram","color":"#9B1096","line_name":"澳門輕軌氹仔線 Linha de Taipa do ML M","name":"澳門輕軌氹仔線 Linha de Taipa do ML M","name:en":"Taipa Line of Macao LRT","name_en":"Taipa Line of Macao LRT","name:zh-Hant":"澳門輕軌氹仔線"}},{"type":"Feature","geometry":{"type":"LineString","coordinates":[[113.5233,22.21004],[113.52347,22.21135],[113.52384,22.21211],[113.5242,22.21257]]},"properties":{"osm_id":835625223,"osm_type":"way","macro_region":"macau","railway_type":"rail","color":"#003DA5","line_name":"珠机城际线","name":"珠机城际线","name:en":"Zhuhai-Zhuhai Airport Intercity Railway","name_en":"Zhuhai-Zhuhai Airport Intercity Railway","name:zh":"珠机城际线"}},{"type":"Feature","geometry":{"type":"LineString","coordinates":[[113.52495,22.21321],[113.52562,22.21358],[113.52645,22.21385],[113.53329,22.21519],[113.53448,22.21556],[113.53895,22.21732],[113.54075,22.21752],[113.54387,22.21756]]},"properties":{"osm_id":835625224,"osm_type":"way","macro_region":"macau","railway_type":"rail","color":"#003DA5","line_name":"珠机城际线","name":"珠机城际线","name:en":"Zhuhai-Zhuhai Airport Intercity Railway","name_en":"Zhuhai-Zhuhai Airport Intercity Railway","name:zh":"珠机城际线"}},{"type":"Feature","geometry":{"type":"LineString","coordinates":[[113.5242,22.21257],[113.52495,22.21321]]},"properties":{"osm_id":835625225,"osm_type":"way","macro_region":"macau","railway_type":"rail","color":"#003DA5","line_name":"珠机城际线","name":"珠机城际线","name:en":"Zhuhai-Zhuhai Airport Intercity Railway","name_en":"Zhuhai-Zhuhai Airport Intercity Railway","name:zh":"珠机城际线"}},{"type":"Feature","geometry":{"type":"LineString","coordinates":[[113.53604,22.10719],[113.53958,22.10879],[113.54008,22.1091],[113.54083,22.10994],[113.54097,22.11043],[113.54109,22.11173],[113.54002,22.13488],[113.53931,22.14591],[113.53871,22.15034],[113.53834,22.15217],[113.53804,22.15326],[113.53704,22.1561],[113.53359,22.16256],[113.53314,22.1631],[113.53282,22.16331],[113.53209,22.16355],[113.52541,22.16459],[113.52327,22.16465],[113.52165,22.16432],[113.52008,22.16422],[113.51886,22.16432],[113.51815,22.1645],[113.5168,22.16519],[113.51598,22.16589],[113.5133,22.16924],[113.51288,22.17012],[113.51266,22.17116],[113.51269,22.17195],[113.51289,22.17273],[113.51316,22.17336],[113.51372,22.17413],[113.51468,22.17501],[113.51683,22.17623],[113.51792,22.177],[113.51891,22.17794],[113.52006,22.17943],[113.52246,22.18448],[113.52319,22.18637],[113.52413,22.18814],[113.52596,22.19043],[113.52883,22.19512],[113.52912,22.19604],[113.52918,22.19895],[113.52912,22.19969],[113.52904,22.20025],[113.52862,22.20126],[113.52783,22.20291],[113.52609,22.2059],[113.52401,22.20798],[113.5237,22.20841],[113.52341,22.20897],[113.52321,22.21004]]},"properties":{"osm_id":835966823,"osm_type":"way","macro_region":"macau","railway_type":"rail","color":"#003DA5","line_name":"珠机城际线","name":"珠机城际线","name:en":"Zhuhai-Zhuhai Airport Intercity Railway","name_en":"Zhuhai-Zhuhai Airport Intercity Railway","name:zh-Hant":"珠機城際線"}},{"type":"Feature","geometry":{"type":"LineString","coordinates":[[113.53816,22.21715],[113.53742,22.21678]]},"properties":{"osm_id":838843786,"osm_type":"way","macro_region":"macau","railway_type":"rail","color":"#003DA5","line_name":"珠海联络线","name":"珠海联络线"}},{"type":"Feature","geometry":{"type":"LineString","coordinates":[[113.5693,22.15007],[113.57103,22.15079],[113.57135,22.15114],[113.57143,22.15145],[113.57135,22.15212],[113.56958,22.15487],[113.5695,22.15522],[113.56961,22.15562],[113.57005,22.156],[113.57362,22.15763],[113.57415,22.15806],[113.57452,22.15876],[113.57475,22.15986],[113.57507,22.16057],[113.57549,22.16201],[113.57542,22.16246],[113.57507,22.16276],[113.57125,22.16369]]},"properties":{"osm_id":850738798,"osm_type":"way","macro_region":"macau","railway_type":"tram","color":"#9B1096","line_name":"澳門輕軌氹仔線 Linha de Taipa do ML M","name":"澳門輕軌氹仔線 Linha de Taipa do ML M","name:en":"Taipa Line of Macao LRT","name_en":"Taipa Line of Macao LRT","name:zh-Hant":"澳門輕軌氹仔線"}},{"type":"Feature","geometry":{"type":"LineString","coordinates":[[113.53555,22.21956],[113.52658,22.23163],[113.52512,22.23322],[113.5214,22.23658]]},"properties":{"osm_id":884000840,"osm_type":"way","macro_region":"macau","railway_type":"highspeed","color":"#E60012","line_name":"广珠城际线","name":"广珠城际线","name:en":"Guangzhou–Zhuhai Intercity Railway","name_en":"Guangzhou–Zhuhai Intercity Railway","name:zh":"广珠城际线"}},{"type":"Feature","geometry":{"type":"LineString","coordinates":[[113.52144,22.23661],[113.5242,22.23413],[113.52613,22.23223],[113.53558,22.21958]]},"properties":{"osm_id":884000841,"osm_type":"way","macro_region":"macau","railway_type":"highspeed","color":"#E60012","line_name":"广珠城际线","name":"广珠城际线","name:en":"Guangzhou–Zhuhai Intercity Railway","name_en":"Guangzhou–Zhuhai Intercity Railway","name:zh":"广珠城际线"}},{"type":"Feature","geometry":{"type":"LineString","coordinates":[[113.53608,22.10711],[113.53963,22.10871],[113.54014,22.10903],[113.54092,22.1099],[113.54106,22.11041],[113.54119,22.11173],[113.54012,22.13488],[113.53941,22.14592],[113.53881,22.15035],[113.53843,22.15219],[113.53813,22.15329],[113.53713,22.15613],[113.53368,22.1626],[113.5332,22.16317],[113.53287,22.16339],[113.53211,22.16364],[113.52541,22.16468],[113.52326,22.16474],[113.52164,22.16441],[113.52008,22.16431],[113.51888,22.1644],[113.51819,22.16458],[113.51686,22.16527],[113.51606,22.16595],[113.51338,22.16929],[113.51297,22.17015],[113.51276,22.17116],[113.51279,22.17194],[113.51298,22.17271],[113.51325,22.17332],[113.5138,22.17408],[113.51474,22.17494],[113.51689,22.17616],[113.51798,22.17694],[113.51897,22.17788],[113.52014,22.17938],[113.52255,22.18445],[113.52328,22.18633],[113.52421,22.18809],[113.52604,22.19038],[113.52892,22.19508],[113.52922,22.19603],[113.52928,22.19896],[113.52922,22.1997],[113.52914,22.20027],[113.52871,22.2013],[113.52791,22.20295],[113.52617,22.20595],[113.52565,22.20655],[113.52409,22.20804],[113.52378,22.20846],[113.52338,22.20939],[113.5233,22.21004]]},"properties":{"osm_id":904642002,"osm_type":"way","macro_region":"macau","railway_type":"rail","color":"#003DA5","line_name":"珠机城际线","name":"珠机城际线","name:en":"Zhuhai-Zhuhai Airport Intercity Railway","name_en":"Zhuhai-Zhuhai Airport Intercity Railway","name:zh-Hant":"珠機城際線"}},{"type":"Feature","geometry":{"type":"LineString","coordinates":[[113.52321,22.21004],[113.5233,22.21091],[113.52345,22.2115],[113.52375,22.2121],[113.52416,22.21262]]},"properties":{"osm_id":904642003,"osm_type":"way","macro_region":"macau","railway_type":"rail","color":"#003DA5","line_name":"珠机城际线","name":"珠机城际线","name:en":"Zhuhai-Zhuhai Airport Intercity Railway","name_en":"Zhuhai-Zhuhai Airport Intercity Railway","name:zh":"珠机城际线"}},{"type":"Feature","geometry":{"type":"LineString","coordinates":[[113.54485,22.14067],[113.54493,22.13938],[113.54519,22.13887],[113.54573,22.13833],[113.54621,22.13809],[113.54681,22.13798],[113.54742,22.138],[113.55095,22.13914],[113.55198,22.13939],[113.55301,22.13947],[113.55504,22.13933]]},"properties":{"osm_id":909486580,"osm_type":"way","macro_region":"macau","railway_type":"tram","color":"#9B1096","line_name":"澳門輕軌橫琴線 Linha de Hengqin do MLM","name":"澳門輕軌橫琴線 Linha de Hengqin do MLM","name:en":"Hengqin Line of Macao LRT","name_en":"Hengqin Line of Macao LRT","name:zh-Hant":"澳門輕軌橫琴線"}},{"type":"Feature","geometry":{"type":"LineString","coordinates":[[113.55504,22.13933],[113.55954,22.139]]},"properties":{"osm_id":909486582,"osm_type":"way","macro_region":"macau","railway_type":"tram","color":"#9B1096","line_name":"澳門輕軌橫琴線 Linha de Hengqin do MLM","name":"澳門輕軌橫琴線 Linha de Hengqin do MLM","name:en":"Hengqin Line of Macao LRT","name_en":"Hengqin Line of Macao LRT","name:zh-Hant":"澳門輕軌橫琴線"}},{"type":"Feature","geometry":{"type":"LineString","coordinates":[[113.49049,22.11577],[113.49233,22.11579],[113.49554,22.11558],[113.49877,22.1151],[113.50076,22.11454],[113.5024,22.11385],[113.51668,22.10579],[113.51887,22.10488],[113.52024,22.10453],[113.52224,22.10422],[113.52409,22.10408],[113.52642,22.10411],[113.5287,22.10429],[113.52948,22.10443],[113.53133,22.10496],[113.53608,22.10711]]},"properties":{"osm_id":919017990,"osm_type":"way","macro_region":"macau","railway_type":"rail","color":"#003DA5","line_name":"珠机城际线","name":"珠机城际线","name:en":"Zhuhai-Zhuhai Airport Intercity Railway","name_en":"Zhuhai-Zhuhai Airport Intercity Railway","name:zh-Hant":"珠機城際線"}},{"type":"Feature","geometry":{"type":"LineString","coordinates":[[113.52954,22.18535],[113.52933,22.1845],[113.52935,22.18389]]},"properties":{"osm_id":1232770752,"osm_type":"way","macro_region":"macau","railway_type":"tram","color":"#9B1096","line_name":"澳門輕軌氹仔線 Linha de Taipa do ML M","name":"澳門輕軌氹仔線 Linha de Taipa do ML M","name:en":"Taipa Line of Macao LRT","name_en":"Taipa Line of Macao LRT","name:zh-Hant":"澳門輕軌氹仔線"}},{"type":"Feature","geometry":{"type":"LineString","coordinates":[[113.52947,22.18342],[113.5294,22.18453],[113.52962,22.18534]]},"properties":{"osm_id":1232770753,"osm_type":"way","macro_region":"macau","railway_type":"tram","color":"#9B1096","line_name":"澳門輕軌氹仔線 Linha de Taipa do ML M","name":"澳門輕軌氹仔線 Linha de Taipa do ML M","name:en":"Taipa Line of Macao LRT","name_en":"Taipa Line of Macao LRT","name:zh-Hant":"澳門輕軌氹仔線"}},{"type":"Feature","geometry":{"type":"LineString","coordinates":[[113.54005,22.21793],[113.53923,22.21769],[113.53816,22.21715]]},"properties":{"osm_id":1249376345,"osm_type":"way","macro_region":"macau","railway_type":"rail","color":"#003DA5","line_name":"珠海联络线","name":"珠海联络线"}},{"type":"Feature","geometry":{"type":"LineString","coordinates":[[113.56336,22.13799],[113.56333,22.13738]]},"properties":{"osm_id":1329949286,"osm_type":"way","macro_region":"macau","railway_type":"tram","color":"#9B1096","line_name":"澳門輕軌石排灣線 Linha de Seac Pai Van do ML M","name":"澳門輕軌石排灣線 Linha de Seac Pai Van do ML M","name:en":"Seac Pai Van Line of Macao LRT","name_en":"Seac Pai Van Line of Macao LRT","name:zh-Hant":"澳門輕軌石排灣線"}},{"type":"Feature","geometry":{"type":"LineString","coordinates":[[113.56047,22.13151],[113.56185,22.13146]]},"properties":{"osm_id":1329949287,"osm_type":"way","macro_region":"macau","railway_type":"tram","color":"#9B1096","line_name":"澳門輕軌石排灣線 Linha de Seac Pai Van do ML M","name":"澳門輕軌石排灣線 Linha de Seac Pai Van do ML M","name:en":"Seac Pai Van Line of Macao LRT","name_en":"Seac Pai Van Line of Macao LRT","name:zh-Hant":"澳門輕軌石排灣線"}},{"type":"Feature","geometry":{"type":"LineString","coordinates":[[113.56123,22.1314],[113.56046,22.13143]]},"properties":{"osm_id":1329949288,"osm_type":"way","macro_region":"macau","railway_type":"tram","color":"#9B1096","line_name":"澳門輕軌石排灣線 Linha de Seac Pai Van do ML M","name":"澳門輕軌石排灣線 Linha de Seac Pai Van do ML M","name:en":"Seac Pai Van Line of Macao LRT","name_en":"Seac Pai Van Line of Macao LRT","name:zh-Hant":"澳門輕軌石排灣線"}},{"type":"Feature","geometry":{"type":"LineString","coordinates":[[113.55954,22.139],[113.55972,22.13898]]},"properties":{"osm_id":1339606703,"osm_type":"way","macro_region":"macau","railway_type":"tram","color":"#9B1096","line_name":"澳門輕軌橫琴線 Linha de Hengqin do ML M","name":"澳門輕軌橫琴線 Linha de Hengqin do ML M","name:en":"Hengqin Line of Macao LRT","name_en":"Hengqin Line of Macao LRT","name:zh-Hant":"澳门轻轨横琴线"}},{"type":"Feature","geometry":{"type":"Point","coordinates":[113.53965,22.14102]},"properties":{"osm_id":2936895090,"osm_type":"node","macro_region":"macau","railway_type":"highspeed","color":"#E60012","name":"横琴","name:en":"Hengqin","name_en":"Hengqin","name:zh":"横琴"}},{"type":"Feature","geometry":{"type":"Point","coordinates":[113.52921,22.19794]},"properties":{"osm_id":2936895093,"osm_type":"node","macro_region":"macau","railway_type":"highspeed","color":"#E60012","name":"湾仔北","name:en":"Wanzaibei (Out of Service)","name_en":"Wanzaibei (Out of Service)","name:zh":"湾仔北"}},{"type":"Feature","geometry":{"type":"Point","coordinates":[113.5157,22.17555]},"properties":{"osm_id":2936895096,"osm_type":"node","macro_region":"macau","railway_type":"highspeed","color":"#E60012","name":"十字门","name:en":"Shizimen","name_en":"Shizimen","name:zh-Hant":"十字門"}},{"type":"Feature","geometry":{"type":"Point","coordinates":[113.55455,22.15087]},"properties":{"osm_id":7051540683,"osm_type":"node","macro_region":"macau","railway_type":"subway","color":"#E3002C","name":"排角 Pai Kok","name:en":"Pai Kok","name_en":"Pai Kok","name:zh-Hant":"排角"}},{"type":"Feature","geometry":{"type":"Point","coordinates":[113.57065,22.15308]},"properties":{"osm_id":7051569786,"osm_type":"node","macro_region":"macau","railway_type":"subway","color":"#E3002C","name":"科大 UCTM","name:en":"MUST","name_en":"MUST","name:zh-Hant":"科大"}},{"type":"Feature","geometry":{"type":"Point","coordinates":[113.56912,22.14826]},"properties":{"osm_id":7051569789,"osm_type":"node","macro_region":"macau","railway_type":"subway","color":"#E3002C","name":"路氹東 Cotai Leste","name:en":"Cotai East","name_en":"Cotai East","name:zh-Hant":"路氹東"}},{"type":"Feature","geometry":{"type":"Point","coordinates":[113.56864,22.14241]},"properties":{"osm_id":7051569792,"osm_type":"node","macro_region":"macau","railway_type":"subway","color":"#E3002C","name":"東亞運 Jogos da Ásia Oriental","name:en":"East Asian Games","name_en":"East Asian Games","name:zh-Hant":"東亞運"}},{"type":"Feature","geometry":{"type":"Point","coordinates":[113.55981,22.13952]},"properties":{"osm_id":7051569795,"osm_type":"node","macro_region":"macau","railway_type":"subway","color":"#E3002C","name":"蓮花 Lótus","name:en":"Lotus","name_en":"Lotus","name:zh-Hant":"蓮花"}},{"type":"Feature","geometry":{"type":"Point","coordinates":[113.55786,22.14509]},"properties":{"osm_id":7051569798,"osm_type":"node","macro_region":"macau","railway_type":"subway","color":"#E3002C","name":"路氹西 Cotai Oeste","name:en":"Cotai West","name_en":"Cotai West","name:zh-Hant":"路氹西"}},{"type":"Feature","geometry":{"type":"Point","coordinates":[113.55188,22.15436]},"properties":{"osm_id":7051569801,"osm_type":"node","macro_region":"macau","railway_type":"subway","color":"#E3002C","name":"運動場 Estádio","name:en":"Stadium Station","name_en":"Stadium Station","name:zh-Hant":"運動場"}},{"type":"Feature","geometry":{"type":"Point","coordinates":[113.54724,22.1571]},"properties":{"osm_id":7051569804,"osm_type":"node","macro_region":"macau","railway_type":"subway","color":"#E3002C","name":"馬會 Jockey Clube","name:en":"Jockey Club","name_en":"Jockey Club","name:zh-Hant":"馬會"}},{"type":"Feature","geometry":{"type":"Point","coordinates":[113.57465,22.1594]},"properties":{"osm_id":7051569807,"osm_type":"node","macro_region":"macau","railway_type":"subway","color":"#E3002C","name":"機場 Aeroporto","name:en":"Airport","name_en":"Airport","name:zh-Hant":"機場"}},{"type":"Feature","geometry":{"type":"Point","coordinates":[113.57387,22.16301]},"properties":{"osm_id":7051569810,"osm_type":"node","macro_region":"macau","railway_type":"subway","color":"#E3002C","name":"氹仔碼頭 Terminal Marítimo da Taipa","name:en":"Taipa Ferry Terminal","name_en":"Taipa Ferry Terminal","name:zh-Hant":"氹仔碼頭"}},{"type":"Feature","geometry":{"type":"Point","coordinates":[113.5413,22.15784]},"properties":{"osm_id":7051569813,"osm_type":"node","macro_region":"macau","railway_type":"subway","color":"#E3002C","name":"海洋 Oceano","name:en":"Ocean","name_en":"Ocean","name:zh-Hant":"海洋"}},{"type":"Feature","geometry":{"type":"Point","coordinates":[113.54394,22.2181]},"properties":{"osm_id":7710011713,"osm_type":"node","macro_region":"macau","railway_type":"rail","color":"#003DA5","name":"珠海","name:en":"Zhuhai","name_en":"Zhuhai","name:zh-Hant":"珠海","name:ja":"珠海"}},{"type":"Feature","geometry":{"type":"Point","coordinates":[113.53606,22.10715]},"properties":{"osm_id":8401353562,"osm_type":"node","macro_region":"macau","railway_type":"highspeed","color":"#E60012","name":"珠海长隆","name:en":"Zhuhaichanglong","name_en":"Zhuhaichanglong","name:zh":"珠海长隆"}},{"type":"Feature","geometry":{"type":"Point","coordinates":[113.56332,22.13871]},"properties":{"osm_id":10132281747,"osm_type":"node","macro_region":"macau","railway_type":"subway","color":"#E3002C","name":"協和醫院 Hospital Union","name:en":"Union Hospital","name_en":"Union Hospital","name:zh-Hant":"協和醫院"}},{"type":"Feature","geometry":{"type":"Point","coordinates":[113.52941,22.18367]},"properties":{"osm_id":11401270262,"osm_type":"node","macro_region":"macau","railway_type":"rail","color":"#003DA5","name":"媽閣 Barra","name:en":"Barra","name_en":"Barra","name:zh-Hant":"媽閣"}},{"type":"Feature","geometry":{"type":"Point","coordinates":[113.56154,22.13142]},"properties":{"osm_id":12304462028,"osm_type":"node","macro_region":"macau","railway_type":"rail","color":"#003DA5","name":"石排灣 Seac Pai Van","name:en":"Seac Pai Van","name_en":"Seac Pai Van","name:zh-Hant":"石排灣"}},{"type":"Feature","geometry":{"type":"Point","coordinates":[113.54492,22.14066]},"properties":{"osm_id":12391564890,"osm_type":"node","macro_region":"macau","railway_type":"rail","color":"#003DA5","name":"橫琴 Hengqin","name:en":"Hengqin","name_en":"Hengqin","name:zh-Hant":"橫琴"}}],"lines":[{"type":"Feature","geometry":{"type":"LineString","coordinates":[[113.54617,22.21797],[113.54153,22.21803]]},"properties":{"osm_id":165636516,"osm_type":"way","macro_region":"macau","railway_type":"highspeed","color":"#E60012","line_name":"广珠城际线","name":"广珠城际线","name:en":"Guangzhou–Zhuhai Intercity Railway","name_en":"Guangzhou–Zhuhai Intercity Railway","name:zh":"广珠城际线"}},{"type":"Feature","geometry":{"type":"LineString","coordinates":[[113.54156,22.15694],[113.54097,22.1587],[113.54075,22.15965],[113.54061,22.16074]]},"properties":{"osm_id":277071239,"osm_type":"way","macro_region":"macau","railway_type":"tram","color":"#9B1096","line_name":"澳門輕軌氹仔線 Linha de Taipa do ML M","name":"澳門輕軌氹仔線 Linha de Taipa do ML M","name:en":"Taipa Line of Macao LRT","name_en":"Taipa Line of Macao LRT","name:zh-Hant":"澳門輕軌氹仔線"}},{"type":"Feature","geometry":{"type":"LineString","coordinates":[[113.54616,22.21782],[113.5415,22.21791]]},"properties":{"osm_id":282682469,"osm_type":"way","macro_region":"macau","railway_type":"rail","color":"#003DA5","line_name":null}},{"type":"Feature","geometry":{"type":"LineString","coordinates":[[113.5415,22.21791],[113.54063,22.21798],[113.54005,22.21793]]},"properties":{"osm_id":282682470,"osm_type":"way","macro_region":"macau","railway_type":"rail","color":"#003DA5","line_name":"珠海联络线","name":"珠海联络线"}},{"type":"Feature","geometry":{"type":"LineString","coordinates":[[113.53604,22.10719],[113.53236,22.1055],[113.53138,22.10512],[113.53055,22.10482],[113.52891,22.10445],[113.52608,22.10423],[113.52396,22.10421],[113.52186,22.10439],[113.52066,22.10459],[113.51871,22.10506],[113.51677,22.10587],[113.50257,22.11388],[113.50099,22.11459],[113.49891,22.11518],[113.49617,22.1156],[113.49418,22.11579],[113.49246,22.11586],[113.49049,22.11581]]},"properties":{"osm_id":290155015,"osm_type":"way","macro_region":"macau","railway_type":"rail","color":"#003DA5","line_name":"珠机城际线","name":"珠机城际线","name:en":"Zhuhai-Zhuhai Airport Intercity Railway","name_en":"Zhuhai-Zhuhai Airport Intercity Railway","name:zh-Hant":"珠機城際線"}},{"type":"Feature","geometry":{"type":"LineString","coordinates":[[113.5693,22.15007],[113.56901,22.14989],[113.56887,22.1496],[113.56918,22.14806],[113.56923,22.14668],[113.56856,22.14171],[113.56843,22.13992],[113.56828,22.13958],[113.56742,22.13886],[113.56707,22.1387],[113.56651,22.13859],[113.56407,22.13877],[113.56259,22.13873],[113.56059,22.13889],[113.5603,22.13901],[113.5593,22.14001],[113.55801,22.1402],[113.5578,22.14033],[113.55767,22.14057],[113.55772,22.1432],[113.558,22.14896],[113.55795,22.14933],[113.55777,22.14965],[113.55731,22.15],[113.55558,22.15043],[113.55171,22.15201],[113.55146,22.15217],[113.55121,22.15253],[113.55119,22.1531]]},"properties":{"osm_id":388893284,"osm_type":"way","macro_region":"macau","railway_type":"tram","color":"#9B1096","line_name":"澳門輕軌氹仔線 Linha de Taipa do ML M","name":"澳門輕軌氹仔線 Linha de Taipa do ML M","name:en":"Taipa Line of Macao LRT","name_en":"Taipa Line of Macao LRT","name:zh-Hant":"澳門輕軌氹仔線"}},{"type":"Feature","geometry":{"type":"LineString","coordinates":[[113.54153,22.21803],[113.53836,22.21808],[113.53742,22.21824],[113.53649,22.21866],[113.53555,22.21956]]},"properties":{"osm_id":402864176,"osm_type":"way","macro_region":"macau","railway_type":"highspeed","color":"#E60012","line_name":"广珠城际线","name":"广珠城际线","name:en":"Guangzhou–Zhuhai Intercity Railway","name_en":"Guangzhou–Zhuhai Intercity Railway","name:zh":"广珠城际线"}},{"type":"Feature","geometry":{"type":"LineString","coordinates":[[113.53558,22.21958],[113.53651,22.21869],[113.53717,22.21836],[113.53788,22.21817],[113.54617,22.21802]]},"properties":{"osm_id":402864182,"osm_type":"way","macro_region":"macau","railway_type":"highspeed","color":"#E60012","line_name":"广珠城际线","name":"广珠城际线","name:en":"Guangzhou–Zhuhai Intercity Railway","name_en":"Guangzhou–Zhuhai Intercity Railway","name:zh":"广珠城际线"}},{"type":"Feature","geometry":{"type":"LineString","coordinates":[[113.54061,22.16074],[113.54037,22.16262],[113.53977,22.16488]]},"properties":{"osm_id":445281246,"osm_type":"way","macro_region":"macau","railway_type":"tram","color":"#9B1096","line_name":"澳門輕軌氹仔線 Linha de Taipa do ML M","name":"澳門輕軌氹仔線 Linha de Taipa do ML M","name:en":"Taipa Line of Macao LRT","name_en":"Taipa Line of Macao LRT","name:zh-Hant":"澳門輕軌氹仔線"}},{"type":"Feature","geometry":{"type":"LineString","coordinates":[[113.52935,22.18389],[113.52955,22.18233],[113.52979,22.18188],[113.53033,22.18124],[113.53075,22.18088],[113.53208,22.18022]]},"properties":{"osm_id":446757088,"osm_type":"way","macro_region":"macau","railway_type":"tram","color":"#9B1096","line_name":"澳門輕軌氹仔線 Linha de Taipa do ML M","name":"澳門輕軌氹仔線 Linha de Taipa do ML M","name:en":"Taipa Line of Macao LRT","name_en":"Taipa Line of Macao LRT","name:zh-Hant":"澳門輕軌氹仔線"}},{"type":"Feature","geometry":{"type":"LineString","coordinates":[[113.53977,22.16488],[113.53941,22.16583]]},"properties":{"osm_id":446757089,"osm_type":"way","macro_region":"macau","railway_type":"tram","color":"#9B1096","line_name":"澳門輕軌氹仔線 Linha de Taipa do ML M","name":"澳門輕軌氹仔線 Linha de Taipa do ML M","name:en":"Taipa Line of Macao LRT","name_en":"Taipa Line of Macao LRT","name:zh":"澳門輕軌氹仔線"}},{"type":"Feature","geometry":{"type":"LineString","coordinates":[[113.54165,22.15696],[113.54196,22.15633],[113.54212,22.1562],[113.54242,22.15612],[113.54277,22.15624],[113.5431,22.15656],[113.54341,22.15673],[113.54426,22.15703],[113.54476,22.15711],[113.54905,22.15713],[113.55129,22.157],[113.55211,22.15678],[113.55277,22.15649],[113.553,22.15628],[113.55305,22.15606],[113.55293,22.15578],[113.55226,22.15508]]},"properties":{"osm_id":520187034,"osm_type":"way","macro_region":"macau","railway_type":"tram","color":"#9B1096","line_name":"澳門輕軌氹仔線 Linha de Taipa do ML M","name":"澳門輕軌氹仔線 Linha de Taipa do ML M","name:en":"Taipa Line of Macao LRT","name_en":"Taipa Line of Macao LRT","name:zh-Hant":"澳門輕軌氹仔線"}},{"type":"Feature","geometry":{"type":"LineString","coordinates":[[113.54165,22.15696],[113.54095,22.15904],[113.54072,22.16074]]},"properties":{"osm_id":520187042,"osm_type":"way","macro_region":"macau","railway_type":"tram","color":"#9B1096","line_name":"澳門輕軌氹仔線 Linha de Taipa do ML M","name":"澳門輕軌氹仔線 Linha de Taipa do ML M","name:en":"Taipa Line of Macao LRT","name_en":"Taipa Line of Macao LRT","name:zh-Hant":"澳門輕軌氹仔線"}},{"type":"Feature","geometry":{"type":"LineString","coordinates":[[113.52416,22.21262],[113.5249,22.21325]]},"properties":{"osm_id":554325762,"osm_type":"way","macro_region":"macau","railway_type":"rail","color":"#003DA5","line_name":"珠机城际线","name":"珠机城际线","name:en":"Zhuhai-Zhuhai Airport Intercity Railway","name_en":"Zhuhai-Zhuhai Airport Intercity Railway","name:zh":"珠机城际线"}},{"type":"Feature","geometry":{"type":"LineString","coordinates":[[113.54072,22.16074],[113.54058,22.16216],[113.5402,22.16385],[113.53987,22.16491]]},"properties":{"osm_id":579113746,"osm_type":"way","macro_region":"macau","railway_type":"tram","color":"#9B1096","line_name":"澳門輕軌氹仔線 Linha de Taipa do ML M","name":"澳門輕軌氹仔線 Linha de Taipa do ML M","name:en":"Taipa Line of Macao LRT","name_en":"Taipa Line of Macao LRT","name:zh-Hant":"澳門輕軌氹仔線"}},{"type":"Feature","geometry":{"type":"LineString","coordinates":[[113.5249,22.21325],[113.52545,22.21358],[113.5267,22.21396],[113.53236,22.21503],[113.53353,22.21532],[113.5351,22.21585],[113.53899,22.21738],[113.54156,22.21765],[113.54386,22.21764]]},"properties":{"osm_id":579283414,"osm_type":"way","macro_region":"macau","railway_type":"rail","color":"#003DA5","line_name":"珠机城际线","name":"珠机城际线","name:en":"Zhuhai-Zhuhai Airport Intercity Railway","name_en":"Zhuhai-Zhuhai Airport Intercity Railway","name:zh":"珠机城际线"}},{"type":"Feature","geometry":{"type":"LineString","coordinates":[[113.56185,22.13146],[113.56226,22.13145],[113.56263,22.13158],[113.56286,22.13185],[113.56295,22.1321],[113.56322,22.13793]]},"properties":{"osm_id":620888026,"osm_type":"way","macro_region":"macau","railway_type":"tram","color":"#9B1096","line_name":"澳門輕軌石排灣線 Linha de Seac Pai Van do ML M","name":"澳門輕軌石排灣線 Linha de Seac Pai Van do ML M","name:en":"Seac Pai Van Line of Macao LRT","name_en":"Seac Pai Van Line of Macao LRT","name:zh-Hant":"澳門輕軌石排灣線"}},{"type":"Feature","geometry":{"type":"LineString","coordinates":[[113.53947,22.16586],[113.53987,22.16491]]},"properties":{"osm_id":624638694,"osm_type":"way","macro_region":"macau","railway_type":"tram","color":"#9B1096","line_name":"澳門輕軌氹仔線 Linha de Taipa do ML M","name":"澳門輕軌氹仔線 Linha de Taipa do ML M","name:en":"Taipa Line of Macao LRT","name_en":"Taipa Line of Macao LRT","name:zh":"澳門輕軌氹仔線"}},{"type":"Feature","geometry":{"type":"LineString","coordinates":[[113.53208,22.18022],[113.53232,22.17993],[113.53318,22.17827],[113.53941,22.16583]]},"properties":{"osm_id":624638696,"osm_type":"way","macro_region":"macau","railway_type":"tram","color":"#9B1096","line_name":"澳門輕軌氹仔線 Linha de Taipa do ML M","name":"澳門輕軌氹仔線 Linha de Taipa do ML M","name:en":"Taipa Line of Macao LRT","name_en":"Taipa Line of Macao LRT","name:zh-Hant":"澳門輕軌氹仔線"}},{"type":"Feature","geometry":{"type":"LineString","coordinates":[[113.53214,22.18024],[113.53243,22.17986],[113.53947,22.16586]]},"properties":{"osm_id":624638697,"osm_type":"way","macro_region":"macau","railway_type":"tram","color":"#9B1096","line_name":"澳門輕軌氹仔線 Linha de Taipa do ML M","name":"澳門輕軌氹仔線 Linha de Taipa do ML M","name:en":"Taipa Line of Macao LRT","name_en":"Taipa Line of Macao LRT","name:zh-Hant":"澳門輕軌氹仔線"}},{"type":"Feature","geometry":{"type":"LineString","coordinates":[[113.53214,22.18024],[113.53192,22.18041],[113.53081,22.18091],[113.52988,22.18194],[113.52965,22.18237],[113.52947,22.18342]]},"properties":{"osm_id":624638698,"osm_type":"way","macro_region":"macau","railway_type":"subway","color":"#E3002C","line_name":"澳門輕軌氹仔線 Linha de Taipa do ML M","name":"澳門輕軌氹仔線 Linha de Taipa do ML M","name:en":"Taipa Line of Macao LRT","name_en":"Taipa Line of Macao LRT","name:zh-Hant":"澳門輕軌氹仔線"}},{"type":"Feature","geometry":{"type":"LineString","coordinates":[[113.56856,22.14211],[113.56919,22.14689],[113.56912,22.14819],[113.56883,22.14943],[113.56884,22.14967],[113.5691,22.15001],[113.57108,22.1509],[113.57129,22.15114],[113.57138,22.15144],[113.57137,22.15184],[113.57125,22.1521],[113.56958,22.15476],[113.56947,22.15507],[113.56954,22.15556],[113.56995,22.156],[113.57352,22.15761],[113.57408,22.15804],[113.57431,22.15837],[113.57451,22.15886],[113.57469,22.15985],[113.57506,22.16073],[113.57544,22.16202],[113.57537,22.16243],[113.57505,22.16271],[113.57123,22.16364]]},"properties":{"osm_id":754856890,"osm_type":"way","macro_region":"macau","railway_type":"tram","color":"#9B1096","line_name":"澳門輕軌氹仔線 Linha de Taipa do ML M","name":"澳門輕軌氹仔線 Linha de Taipa do ML M","name:en":"Taipa Line of Macao LRT","name_en":"Taipa Line of Macao LRT","name:zh-Hant":"澳門輕軌氹仔線"}},{"type":"Feature","geometry":{"type":"LineString","coordinates":[[113.56333,22.13738],[113.56314,22.13535],[113.56296,22.13194],[113.56271,22.13158],[113.56247,22.13142],[113.56123,22.1314]]},"properties":{"osm_id":774703405,"osm_type":"way","macro_region":"macau","railway_type":"tram","color":"#9B1096","line_name":"澳門輕軌石排灣線 Linha de Seac Pai Van do ML M","name":"澳門輕軌石排灣線 Linha de Seac Pai Van do ML M","name:en":"Seac Pai Van Line of Macao LRT","name_en":"Seac Pai Van Line of Macao LRT","name:zh-Hant":"澳門輕軌石排灣線"}},{"type":"Feature","geometry":{"type":"LineString","coordinates":[[113.55226,22.15508],[113.55125,22.15307]]},"properties":{"osm_id":814635017,"osm_type":"way","macro_region":"macau","railway_type":"tram","color":"#9B1096","line_name":"澳門輕軌氹仔線 Linha de Taipa do ML M","name":"澳門輕軌氹仔線 Linha de Taipa do ML M","name:en":"Taipa Line of Macao LRT","name_en":"Taipa Line of Macao LRT","name:zh":"澳門輕軌氹仔線"}},{"type":"Feature","geometry":{"type":"LineString","coordinates":[[113.5522,22.1551],[113.55289,22.15582],[113.55298,22.156],[113.55297,22.1562],[113.55274,22.15644],[113.55177,22.15684],[113.55128,22.15695],[113.54907,22.15708],[113.54483,22.15706],[113.54425,22.15697],[113.54339,22.15667],[113.5428,22.15618],[113.54238,22.15606],[113.54196,22.15621],[113.54156,22.15694]]},"properties":{"osm_id":814635018,"osm_type":"way","macro_region":"macau","railway_type":"tram","color":"#9B1096","line_name":"澳門輕軌氹仔線 Linha de Taipa do ML M","name":"澳門輕軌氹仔線 Linha de Taipa do ML M","name:en":"Taipa Line of Macao LRT","name_en":"Taipa Line of Macao LRT","name:zh-Hant":"澳門輕軌氹仔線"}},{"type":"Feature","geometry":{"type":"LineString","coordinates":[[113.55119,22.1531],[113.5522,22.1551]]},"properties":{"osm_id":814979932,"osm_type":"way","macro_region":"macau","railway_type":"tram","color":"#9B1096","line_name":"澳門輕軌氹仔線 Linha de Taipa do ML M","name":"澳門輕軌氹仔線 Linha de Taipa do ML M","name:en":"Taipa Line of Macao LRT","name_en":"Taipa Line of Macao LRT","name:zh":"澳門輕軌氹仔線"}},{"type":"Feature","geometry":{"type":"LineString","coordinates":[[113.55125,22.15307],[113.55127,22.15255],[113.5515,22.15221],[113.55174,22.15206],[113.55567,22.15045],[113.55738,22.15003],[113.55759,22.14991],[113.55794,22.14949],[113.55805,22.1489],[113.55773,22.14068],[113.55774,22.14054],[113.5579,22.14033],[113.5582,22.14021],[113.55912,22.14014],[113.55932,22.14006],[113.56025,22.13911],[113.56066,22.13893],[113.56258,22.13877],[113.56404,22.13881],[113.56669,22.13865],[113.56755,22.13899],[113.56808,22.13942],[113.56831,22.13971],[113.56839,22.13995],[113.56856,22.14211]]},"properties":{"osm_id":814979933,"osm_type":"way","macro_region":"macau","railway_type":"tram","color":"#9B1096","line_name":"澳門輕軌氹仔線 Linha de Taipa do ML M","name":"澳門輕軌氹仔線 Linha de Taipa do ML M","name:en":"Taipa Line of Macao LRT","name_en":"Taipa Line of Macao LRT","name:zh-Hant":"澳門輕軌氹仔線"}},{"type":"Feature","geometry":{"type":"LineString","coordinates":[[113.5233,22.21004],[113.52347,22.21135],[113.52384,22.21211],[113.5242,22.21257]]},"properties":{"osm_id":835625223,"osm_type":"way","macro_region":"macau","railway_type":"rail","color":"#003DA5","line_name":"珠机城际线","name":"珠机城际线","name:en":"Zhuhai-Zhuhai Airport Intercity Railway","name_en":"Zhuhai-Zhuhai Airport Intercity Railway","name:zh":"珠机城际线"}},{"type":"Feature","geometry":{"type":"LineString","coordinates":[[113.52495,22.21321],[113.52562,22.21358],[113.52645,22.21385],[113.53329,22.21519],[113.53448,22.21556],[113.53895,22.21732],[113.54075,22.21752],[113.54387,22.21756]]},"properties":{"osm_id":835625224,"osm_type":"way","macro_region":"macau","railway_type":"rail","color":"#003DA5","line_name":"珠机城际线","name":"珠机城际线","name:en":"Zhuhai-Zhuhai Airport Intercity Railway","name_en":"Zhuhai-Zhuhai Airport Intercity Railway","name:zh":"珠机城际线"}},{"type":"Feature","geometry":{"type":"LineString","coordinates":[[113.5242,22.21257],[113.52495,22.21321]]},"properties":{"osm_id":835625225,"osm_type":"way","macro_region":"macau","railway_type":"rail","color":"#003DA5","line_name":"珠机城际线","name":"珠机城际线","name:en":"Zhuhai-Zhuhai Airport Intercity Railway","name_en":"Zhuhai-Zhuhai Airport Intercity Railway","name:zh":"珠机城际线"}},{"type":"Feature","geometry":{"type":"LineString","coordinates":[[113.53604,22.10719],[113.53958,22.10879],[113.54008,22.1091],[113.54083,22.10994],[113.54097,22.11043],[113.54109,22.11173],[113.54002,22.13488],[113.53931,22.14591],[113.53871,22.15034],[113.53834,22.15217],[113.53804,22.15326],[113.53704,22.1561],[113.53359,22.16256],[113.53314,22.1631],[113.53282,22.16331],[113.53209,22.16355],[113.52541,22.16459],[113.52327,22.16465],[113.52165,22.16432],[113.52008,22.16422],[113.51886,22.16432],[113.51815,22.1645],[113.5168,22.16519],[113.51598,22.16589],[113.5133,22.16924],[113.51288,22.17012],[113.51266,22.17116],[113.51269,22.17195],[113.51289,22.17273],[113.51316,22.17336],[113.51372,22.17413],[113.51468,22.17501],[113.51683,22.17623],[113.51792,22.177],[113.51891,22.17794],[113.52006,22.17943],[113.52246,22.18448],[113.52319,22.18637],[113.52413,22.18814],[113.52596,22.19043],[113.52883,22.19512],[113.52912,22.19604],[113.52918,22.19895],[113.52912,22.19969],[113.52904,22.20025],[113.52862,22.20126],[113.52783,22.20291],[113.52609,22.2059],[113.52401,22.20798],[113.5237,22.20841],[113.52341,22.20897],[113.52321,22.21004]]},"properties":{"osm_id":835966823,"osm_type":"way","macro_region":"macau","railway_type":"rail","color":"#003DA5","line_name":"珠机城际线","name":"珠机城际线","name:en":"Zhuhai-Zhuhai Airport Intercity Railway","name_en":"Zhuhai-Zhuhai Airport Intercity Railway","name:zh-Hant":"珠機城際線"}},{"type":"Feature","geometry":{"type":"LineString","coordinates":[[113.53816,22.21715],[113.53742,22.21678]]},"properties":{"osm_id":838843786,"osm_type":"way","macro_region":"macau","railway_type":"rail","color":"#003DA5","line_name":"珠海联络线","name":"珠海联络线"}},{"type":"Feature","geometry":{"type":"LineString","coordinates":[[113.5693,22.15007],[113.57103,22.15079],[113.57135,22.15114],[113.57143,22.15145],[113.57135,22.15212],[113.56958,22.15487],[113.5695,22.15522],[113.56961,22.15562],[113.57005,22.156],[113.57362,22.15763],[113.57415,22.15806],[113.57452,22.15876],[113.57475,22.15986],[113.57507,22.16057],[113.57549,22.16201],[113.57542,22.16246],[113.57507,22.16276],[113.57125,22.16369]]},"properties":{"osm_id":850738798,"osm_type":"way","macro_region":"macau","railway_type":"tram","color":"#9B1096","line_name":"澳門輕軌氹仔線 Linha de Taipa do ML M","name":"澳門輕軌氹仔線 Linha de Taipa do ML M","name:en":"Taipa Line of Macao LRT","name_en":"Taipa Line of Macao LRT","name:zh-Hant":"澳門輕軌氹仔線"}},{"type":"Feature","geometry":{"type":"LineString","coordinates":[[113.53555,22.21956],[113.52658,22.23163],[113.52512,22.23322],[113.5214,22.23658]]},"properties":{"osm_id":884000840,"osm_type":"way","macro_region":"macau","railway_type":"highspeed","color":"#E60012","line_name":"广珠城际线","name":"广珠城际线","name:en":"Guangzhou–Zhuhai Intercity Railway","name_en":"Guangzhou–Zhuhai Intercity Railway","name:zh":"广珠城际线"}},{"type":"Feature","geometry":{"type":"LineString","coordinates":[[113.52144,22.23661],[113.5242,22.23413],[113.52613,22.23223],[113.53558,22.21958]]},"properties":{"osm_id":884000841,"osm_type":"way","macro_region":"macau","railway_type":"highspeed","color":"#E60012","line_name":"广珠城际线","name":"广珠城际线","name:en":"Guangzhou–Zhuhai Intercity Railway","name_en":"Guangzhou–Zhuhai Intercity Railway","name:zh":"广珠城际线"}},{"type":"Feature","geometry":{"type":"LineString","coordinates":[[113.53608,22.10711],[113.53963,22.10871],[113.54014,22.10903],[113.54092,22.1099],[113.54106,22.11041],[113.54119,22.11173],[113.54012,22.13488],[113.53941,22.14592],[113.53881,22.15035],[113.53843,22.15219],[113.53813,22.15329],[113.53713,22.15613],[113.53368,22.1626],[113.5332,22.16317],[113.53287,22.16339],[113.53211,22.16364],[113.52541,22.16468],[113.52326,22.16474],[113.52164,22.16441],[113.52008,22.16431],[113.51888,22.1644],[113.51819,22.16458],[113.51686,22.16527],[113.51606,22.16595],[113.51338,22.16929],[113.51297,22.17015],[113.51276,22.17116],[113.51279,22.17194],[113.51298,22.17271],[113.51325,22.17332],[113.5138,22.17408],[113.51474,22.17494],[113.51689,22.17616],[113.51798,22.17694],[113.51897,22.17788],[113.52014,22.17938],[113.52255,22.18445],[113.52328,22.18633],[113.52421,22.18809],[113.52604,22.19038],[113.52892,22.19508],[113.52922,22.19603],[113.52928,22.19896],[113.52922,22.1997],[113.52914,22.20027],[113.52871,22.2013],[113.52791,22.20295],[113.52617,22.20595],[113.52565,22.20655],[113.52409,22.20804],[113.52378,22.20846],[113.52338,22.20939],[113.5233,22.21004]]},"properties":{"osm_id":904642002,"osm_type":"way","macro_region":"macau","railway_type":"rail","color":"#003DA5","line_name":"珠机城际线","name":"珠机城际线","name:en":"Zhuhai-Zhuhai Airport Intercity Railway","name_en":"Zhuhai-Zhuhai Airport Intercity Railway","name:zh-Hant":"珠機城際線"}},{"type":"Feature","geometry":{"type":"LineString","coordinates":[[113.52321,22.21004],[113.5233,22.21091],[113.52345,22.2115],[113.52375,22.2121],[113.52416,22.21262]]},"properties":{"osm_id":904642003,"osm_type":"way","macro_region":"macau","railway_type":"rail","color":"#003DA5","line_name":"珠机城际线","name":"珠机城际线","name:en":"Zhuhai-Zhuhai Airport Intercity Railway","name_en":"Zhuhai-Zhuhai Airport Intercity Railway","name:zh":"珠机城际线"}},{"type":"Feature","geometry":{"type":"LineString","coordinates":[[113.54485,22.14067],[113.54493,22.13938],[113.54519,22.13887],[113.54573,22.13833],[113.54621,22.13809],[113.54681,22.13798],[113.54742,22.138],[113.55095,22.13914],[113.55198,22.13939],[113.55301,22.13947],[113.55504,22.13933]]},"properties":{"osm_id":909486580,"osm_type":"way","macro_region":"macau","railway_type":"tram","color":"#9B1096","line_name":"澳門輕軌橫琴線 Linha de Hengqin do MLM","name":"澳門輕軌橫琴線 Linha de Hengqin do MLM","name:en":"Hengqin Line of Macao LRT","name_en":"Hengqin Line of Macao LRT","name:zh-Hant":"澳門輕軌橫琴線"}},{"type":"Feature","geometry":{"type":"LineString","coordinates":[[113.55504,22.13933],[113.55954,22.139]]},"properties":{"osm_id":909486582,"osm_type":"way","macro_region":"macau","railway_type":"tram","color":"#9B1096","line_name":"澳門輕軌橫琴線 Linha de Hengqin do MLM","name":"澳門輕軌橫琴線 Linha de Hengqin do MLM","name:en":"Hengqin Line of Macao LRT","name_en":"Hengqin Line of Macao LRT","name:zh-Hant":"澳門輕軌橫琴線"}},{"type":"Feature","geometry":{"type":"LineString","coordinates":[[113.49049,22.11577],[113.49233,22.11579],[113.49554,22.11558],[113.49877,22.1151],[113.50076,22.11454],[113.5024,22.11385],[113.51668,22.10579],[113.51887,22.10488],[113.52024,22.10453],[113.52224,22.10422],[113.52409,22.10408],[113.52642,22.10411],[113.5287,22.10429],[113.52948,22.10443],[113.53133,22.10496],[113.53608,22.10711]]},"properties":{"osm_id":919017990,"osm_type":"way","macro_region":"macau","railway_type":"rail","color":"#003DA5","line_name":"珠机城际线","name":"珠机城际线","name:en":"Zhuhai-Zhuhai Airport Intercity Railway","name_en":"Zhuhai-Zhuhai Airport Intercity Railway","name:zh-Hant":"珠機城際線"}},{"type":"Feature","geometry":{"type":"LineString","coordinates":[[113.52954,22.18535],[113.52933,22.1845],[113.52935,22.18389]]},"properties":{"osm_id":1232770752,"osm_type":"way","macro_region":"macau","railway_type":"tram","color":"#9B1096","line_name":"澳門輕軌氹仔線 Linha de Taipa do ML M","name":"澳門輕軌氹仔線 Linha de Taipa do ML M","name:en":"Taipa Line of Macao LRT","name_en":"Taipa Line of Macao LRT","name:zh-Hant":"澳門輕軌氹仔線"}},{"type":"Feature","geometry":{"type":"LineString","coordinates":[[113.52947,22.18342],[113.5294,22.18453],[113.52962,22.18534]]},"properties":{"osm_id":1232770753,"osm_type":"way","macro_region":"macau","railway_type":"tram","color":"#9B1096","line_name":"澳門輕軌氹仔線 Linha de Taipa do ML M","name":"澳門輕軌氹仔線 Linha de Taipa do ML M","name:en":"Taipa Line of Macao LRT","name_en":"Taipa Line of Macao LRT","name:zh-Hant":"澳門輕軌氹仔線"}},{"type":"Feature","geometry":{"type":"LineString","coordinates":[[113.54005,22.21793],[113.53923,22.21769],[113.53816,22.21715]]},"properties":{"osm_id":1249376345,"osm_type":"way","macro_region":"macau","railway_type":"rail","color":"#003DA5","line_name":"珠海联络线","name":"珠海联络线"}},{"type":"Feature","geometry":{"type":"LineString","coordinates":[[113.56336,22.13799],[113.56333,22.13738]]},"properties":{"osm_id":1329949286,"osm_type":"way","macro_region":"macau","railway_type":"tram","color":"#9B1096","line_name":"澳門輕軌石排灣線 Linha de Seac Pai Van do ML M","name":"澳門輕軌石排灣線 Linha de Seac Pai Van do ML M","name:en":"Seac Pai Van Line of Macao LRT","name_en":"Seac Pai Van Line of Macao LRT","name:zh-Hant":"澳門輕軌石排灣線"}},{"type":"Feature","geometry":{"type":"LineString","coordinates":[[113.56047,22.13151],[113.56185,22.13146]]},"properties":{"osm_id":1329949287,"osm_type":"way","macro_region":"macau","railway_type":"tram","color":"#9B1096","line_name":"澳門輕軌石排灣線 Linha de Seac Pai Van do ML M","name":"澳門輕軌石排灣線 Linha de Seac Pai Van do ML M","name:en":"Seac Pai Van Line of Macao LRT","name_en":"Seac Pai Van Line of Macao LRT","name:zh-Hant":"澳門輕軌石排灣線"}},{"type":"Feature","geometry":{"type":"LineString","coordinates":[[113.56123,22.1314],[113.56046,22.13143]]},"properties":{"osm_id":1329949288,"osm_type":"way","macro_region":"macau","railway_type":"tram","color":"#9B1096","line_name":"澳門輕軌石排灣線 Linha de Seac Pai Van do ML M","name":"澳門輕軌石排灣線 Linha de Seac Pai Van do ML M","name:en":"Seac Pai Van Line of Macao LRT","name_en":"Seac Pai Van Line of Macao LRT","name:zh-Hant":"澳門輕軌石排灣線"}},{"type":"Feature","geometry":{"type":"LineString","coordinates":[[113.55954,22.139],[113.55972,22.13898]]},"properties":{"osm_id":1339606703,"osm_type":"way","macro_region":"macau","railway_type":"tram","color":"#9B1096","line_name":"澳門輕軌橫琴線 Linha de Hengqin do ML M","name":"澳門輕軌橫琴線 Linha de Hengqin do ML M","name:en":"Hengqin Line of Macao LRT","name_en":"Hengqin Line of Macao LRT","name:zh-Hant":"澳门轻轨横琴线"}}],"stations":[{"type":"Feature","geometry":{"type":"Point","coordinates":[113.53965,22.14102]},"properties":{"osm_id":2936895090,"osm_type":"node","macro_region":"macau","railway_type":"highspeed","color":"#E60012","name":"横琴","name:en":"Hengqin","name_en":"Hengqin","name:zh":"横琴"}},{"type":"Feature","geometry":{"type":"Point","coordinates":[113.52921,22.19794]},"properties":{"osm_id":2936895093,"osm_type":"node","macro_region":"macau","railway_type":"highspeed","color":"#E60012","name":"湾仔北","name:en":"Wanzaibei (Out of Service)","name_en":"Wanzaibei (Out of Service)","name:zh":"湾仔北"}},{"type":"Feature","geometry":{"type":"Point","coordinates":[113.5157,22.17555]},"properties":{"osm_id":2936895096,"osm_type":"node","macro_region":"macau","railway_type":"highspeed","color":"#E60012","name":"十字门","name:en":"Shizimen","name_en":"Shizimen","name:zh-Hant":"十字門"}},{"type":"Feature","geometry":{"type":"Point","coordinates":[113.55455,22.15087]},"properties":{"osm_id":7051540683,"osm_type":"node","macro_region":"macau","railway_type":"subway","color":"#E3002C","name":"排角 Pai Kok","name:en":"Pai Kok","name_en":"Pai Kok","name:zh-Hant":"排角"}},{"type":"Feature","geometry":{"type":"Point","coordinates":[113.57065,22.15308]},"properties":{"osm_id":7051569786,"osm_type":"node","macro_region":"macau","railway_type":"subway","color":"#E3002C","name":"科大 UCTM","name:en":"MUST","name_en":"MUST","name:zh-Hant":"科大"}},{"type":"Feature","geometry":{"type":"Point","coordinates":[113.56912,22.14826]},"properties":{"osm_id":7051569789,"osm_type":"node","macro_region":"macau","railway_type":"subway","color":"#E3002C","name":"路氹東 Cotai Leste","name:en":"Cotai East","name_en":"Cotai East","name:zh-Hant":"路氹東"}},{"type":"Feature","geometry":{"type":"Point","coordinates":[113.56864,22.14241]},"properties":{"osm_id":7051569792,"osm_type":"node","macro_region":"macau","railway_type":"subway","color":"#E3002C","name":"東亞運 Jogos da Ásia Oriental","name:en":"East Asian Games","name_en":"East Asian Games","name:zh-Hant":"東亞運"}},{"type":"Feature","geometry":{"type":"Point","coordinates":[113.55981,22.13952]},"properties":{"osm_id":7051569795,"osm_type":"node","macro_region":"macau","railway_type":"subway","color":"#E3002C","name":"蓮花 Lótus","name:en":"Lotus","name_en":"Lotus","name:zh-Hant":"蓮花"}},{"type":"Feature","geometry":{"type":"Point","coordinates":[113.55786,22.14509]},"properties":{"osm_id":7051569798,"osm_type":"node","macro_region":"macau","railway_type":"subway","color":"#E3002C","name":"路氹西 Cotai Oeste","name:en":"Cotai West","name_en":"Cotai West","name:zh-Hant":"路氹西"}},{"type":"Feature","geometry":{"type":"Point","coordinates":[113.55188,22.15436]},"properties":{"osm_id":7051569801,"osm_type":"node","macro_region":"macau","railway_type":"subway","color":"#E3002C","name":"運動場 Estádio","name:en":"Stadium Station","name_en":"Stadium Station","name:zh-Hant":"運動場"}},{"type":"Feature","geometry":{"type":"Point","coordinates":[113.54724,22.1571]},"properties":{"osm_id":7051569804,"osm_type":"node","macro_region":"macau","railway_type":"subway","color":"#E3002C","name":"馬會 Jockey Clube","name:en":"Jockey Club","name_en":"Jockey Club","name:zh-Hant":"馬會"}},{"type":"Feature","geometry":{"type":"Point","coordinates":[113.57465,22.1594]},"properties":{"osm_id":7051569807,"osm_type":"node","macro_region":"macau","railway_type":"subway","color":"#E3002C","name":"機場 Aeroporto","name:en":"Airport","name_en":"Airport","name:zh-Hant":"機場"}},{"type":"Feature","geometry":{"type":"Point","coordinates":[113.57387,22.16301]},"properties":{"osm_id":7051569810,"osm_type":"node","macro_region":"macau","railway_type":"subway","color":"#E3002C","name":"氹仔碼頭 Terminal Marítimo da Taipa","name:en":"Taipa Ferry Terminal","name_en":"Taipa Ferry Terminal","name:zh-Hant":"氹仔碼頭"}},{"type":"Feature","geometry":{"type":"Point","coordinates":[113.5413,22.15784]},"properties":{"osm_id":7051569813,"osm_type":"node","macro_region":"macau","railway_type":"subway","color":"#E3002C","name":"海洋 Oceano","name:en":"Ocean","name_en":"Ocean","name:zh-Hant":"海洋"}},{"type":"Feature","geometry":{"type":"Point","coordinates":[113.54394,22.2181]},"properties":{"osm_id":7710011713,"osm_type":"node","macro_region":"macau","railway_type":"rail","color":"#003DA5","name":"珠海","name:en":"Zhuhai","name_en":"Zhuhai","name:zh-Hant":"珠海","name:ja":"珠海"}},{"type":"Feature","geometry":{"type":"Point","coordinates":[113.53606,22.10715]},"properties":{"osm_id":8401353562,"osm_type":"node","macro_region":"macau","railway_type":"highspeed","color":"#E60012","name":"珠海长隆","name:en":"Zhuhaichanglong","name_en":"Zhuhaichanglong","name:zh":"珠海长隆"}},{"type":"Feature","geometry":{"type":"Point","coordinates":[113.56332,22.13871]},"properties":{"osm_id":10132281747,"osm_type":"node","macro_region":"macau","railway_type":"subway","color":"#E3002C","name":"協和醫院 Hospital Union","name:en":"Union Hospital","name_en":"Union Hospital","name:zh-Hant":"協和醫院"}},{"type":"Feature","geometry":{"type":"Point","coordinates":[113.52941,22.18367]},"properties":{"osm_id":11401270262,"osm_type":"node","macro_region":"macau","railway_type":"rail","color":"#003DA5","name":"媽閣 Barra","name:en":"Barra","name_en":"Barra","name:zh-Hant":"媽閣"}},{"type":"Feature","geometry":{"type":"Point","coordinates":[113.56154,22.13142]},"properties":{"osm_id":12304462028,"osm_type":"node","macro_region":"macau","railway_type":"rail","color":"#003DA5","name":"石排灣 Seac Pai Van","name:en":"Seac Pai Van","name_en":"Seac Pai Van","name:zh-Hant":"石排灣"}},{"type":"Feature","geometry":{"type":"Point","coordinates":[113.54492,22.14066]},"properties":{"osm_id":12391564890,"osm_type":"node","macro_region":"macau","railway_type":"rail","color":"#003DA5","name":"橫琴 Hengqin","name:en":"Hengqin","name_en":"Hengqin","name:zh-Hant":"橫琴"}}],"stats":{"lines":47,"stations":20}}